crop_lca/__init__.py
crop_lca/database/__init__.py
crop_lca/database/crop_database.db
crop_lca/geo_crop_lca/__init__.py
crop_lca/geo_crop_lca/catchment_crop_generator.py
crop_lca/geo_crop_lca/catchment_crop_production.py
crop_lca/lca.py
crop_lca/models.py
crop_lca/national_crop_production.py
crop_lca/resource_manager/__init__.py
crop_lca/resource_manager/crop_lca_data_manager.py
crop_lca/resource_manager/data_loader.py
crop_lca/resource_manager/database_manager.py
crop_lca-0.2.2.dist-info/LICENSE
crop_lca-0.2.2.dist-info/METADATA
crop_lca-0.2.2.dist-info/WHEEL
crop_lca-0.2.2.dist-info/RECORD
